quran/__init__.py
quran/ajza.py
quran/chapters.py
quran/translation.py
quran/verses.py
quran.py-0.1.dist-info/LICENSE
quran.py-0.1.dist-info/METADATA
quran.py-0.1.dist-info/WHEEL
quran.py-0.1.dist-info/top_level.txt
quran.py-0.1.dist-info/RECORD
