Metadata-Version: 2.1
Name: quran.py
Version: 0.1
Summary: An API wrapper for Quran.com written in Python.
Home-page: https://github.com/Jadtz/quran.py
Author: Jadtz
Author-email: amjid482@gmail.com
License: UNKNOWN
Project-URL: Bug Tracker, https://github.com/Jadtz/quran.py/issues
Platform: UNKNOWN
Classifier: Programming Language :: Python :: 3
Classifier: License :: OSI Approved :: MIT License
Classifier: Operating System :: OS Independent
Requires-Python: >=3.8
Requires-Dist: certifi (==2020.12.5)
Requires-Dist: chardet (==4.0.0)
Requires-Dist: idna (==2.10)
Requires-Dist: requests (==2.25.1)
Requires-Dist: urllib3 (==1.26.4)
